{"builds":[{"threat":2,"pilots":[{"id":"Jedi Knight","upgrades":{"configuration":["Delta-7B"]}}]},{"threat":3,"pilots":[{"id":"Obi-Wan Kenobi","upgrades":{"force-power":["Predictive Shot"],"astromech":["R4-P17"],"modification":["Spare Parts Canisters"],"configuration":["Calibrated Laser Targeting"]}}]},{"threat":3,"pilots":[{"id":"Plo Koon","upgrades":{"force-power":["Battle Meditation","Sense"],"astromech":["R4-P Astromech"],"modification":["Shield Upgrade"]}}]},{"threat":3,"pilots":[{"id":"Saesee Tiin","upgrades":{"force-power":["Supernatural Reflexes"],"astromech":["R4-P Astromech"],"configuration":["Delta-7B"]}}]},{"threat":4,"pilots":[{"id":"Mace Windu","upgrades":{"force-power":["Supernatural Reflexes"],"astromech":["R2 Astromech"],"configuration":["Delta-7B"],"modification":["Afterburners","Shield Upgrade"]}}]},{"threat":3,"pilots":[{"id":"Anakin Skywalker","upgrades":{"force-power":["Supernatural Reflexes"],"configuration":["Calibrated Laser Targeting"]}}]},{"threat":2,"pilots":[{"id":"Ahsoka Tano","upgrades":{"force-power":["Battle Meditation"],"astromech":["R4-P Astromech"]}}]},{"threat":2,"pilots":[{"id":"Barriss Offee","upgrades":{"force-power":["Sense"],"astromech":["R2 Astromech"]}}]},{"threat":3,"pilots":[{"id":"Luminara Unduli","upgrades":{"force-power":["Brilliant Evasion"],"astromech":["R4-P Astromech"],"configuration":["Delta-7B"],"modification":["Shield Upgrade"]}}]}],"ship":"Delta-7 Aethersprite"}